specifipy/__init__.py
specifipy/diagram_engines/__init__.py
specifipy/diagram_engines/hashable_connection.py
specifipy/file_scanners/__init__.py
specifipy/file_scanners/directory_scanner.py
specifipy/parsers/__init__.py
specifipy/parsers/diagram_generator_d2.py
specifipy/parsers/generic_parser.py
specifipy/parsers/results.py
specifipy/parsers/structure/__init__.py
specifipy/parsers/structure/code_structure_definitions.py
specifipy-0.3.1.dist-info/LICENSE
specifipy-0.3.1.dist-info/METADATA
specifipy-0.3.1.dist-info/WHEEL
specifipy-0.3.1.dist-info/RECORD
